zmqf/__init__.py
zmqf/client/__init__.py
zmqf/client/zmqf_client.py
zmqf/core/__init__.py
zmqf/core/base.py
zmqf/core/broker.py
zmqf/core/exception.py
zmqf/core/utils.py
zmqf/examples/__init__.py
zmqf/examples/mpbs/__init__.py
zmqf/examples/mpbs/mpbs_broker.py
zmqf/examples/mpbs/mpbs_client.py
zmqf/examples/mpbs/mpbs_server.py
zmqf/examples/mpup/__init__.py
zmqf/examples/mpup/broker.py
zmqf/examples/mpup/client.py
zmqf/examples/mpup/server.py
zmqf/examples/mrer/__init__.py
zmqf/examples/mrer/broker.py
zmqf/examples/mrer/client.py
zmqf/examples/mrer/server.py
zmqf/utils/__init__.py
zmqf/utils/zmqf_utils.py
zmqf-0.0.3.dist-info/DESCRIPTION.rst
zmqf-0.0.3.dist-info/METADATA
zmqf-0.0.3.dist-info/RECORD
zmqf-0.0.3.dist-info/WHEEL
zmqf-0.0.3.dist-info/metadata.json
zmqf-0.0.3.dist-info/top_level.txt
