Metadata-Version: 2.0
Name: zmqf
Version: 0.0.3
Summary: zmq based MultiClient-Broker-MultiWorker framework
Home-page: http://www.example.com
Author: kevin90116
Author-email: kevin90116@gmail.com
License: UNKNOWN
Platform: any
Requires-Dist: pyzmq
